setup.cfg
setup.py
src/versiontag.py
src/mako_version_tag.egg-info/PKG-INFO
src/mako_version_tag.egg-info/SOURCES.txt
src/mako_version_tag.egg-info/dependency_links.txt
src/mako_version_tag.egg-info/requires.txt
src/mako_version_tag.egg-info/top_level.txt
test/test_versiontag.py