Metadata-Version: 1.0
Name: mako-version-tag
Version: 1.0
Summary: Displays pkg_resources distribution versions in Mako templates
Home-page: http://alchemy.grimoire.ca/python/sites/mako-version-tag/
Author: Owen Jacobson
Author-email: owen.jacobson@grimoire.ca
License: UNKNOWN
Download-URL: http://alchemy.grimoire.ca/python/releases/mako-version-tag/
Platform: UNKNOWN
Classifier: Development Status :: 4 - Beta
Classifier: Environment :: Web Environment
Classifier: Intended Audience :: Developers
Classifier: License :: OSI Approved :: MIT License
Classifier: Operating System :: OS Independent
Classifier: Topic :: Internet :: WWW/HTTP :: Dynamic Content
Classifier: Topic :: Software Development :: Libraries :: Python Modules
